[{"created":"20241115101140274","creator":"Syretia","text":"### [Click here for the Pling Store application which can be used to download and apply themes on any setup](https://www.pling.com/p/1972991/)\n### [Xfce](https://github.com/NicoHood/NicoHood.github.io/wiki/Xfce4-Desktop-Environment-Customization)\n### [MATE](https://www.addictivetips.com/ubuntu-linux-tips/customize-the-mate-desktop/)\n### [LXQt](https://github.com/simoniz0r/guides/wiki/LXQt-Customizaton)\n### [KDE](https://userbase.kde.org/System_Settings#Workspace_Theme)\n### [GNOME](https://itsfoss.com/gnome-tricks-ubuntu/)\n### [Enlightenment](https://wiki.archlinux.org/index.php/enlightenment)\n### [Cinnamon](https://www.lifewire.com/customize-cinnamon-desktop-environment-linux-mint-2202086)\n### [Budgie](https://www.addictivetips.com/ubuntu-linux-tips/customize-the-budgie-desktop/)\n\n<br>\n\n*This entry is outdated and needs updating.*","tags":"Linux","title":"customization","modified":"20241115101705145","modifier":"Syretia","type":"text/markdown","caption":"Customization","author_url":"https://discordlinux.github.io/wiki/#customization","author_icon":"https://cdn.discordapp.com/emojis/585665071938666508.png","embed_color":"#5865F2"}]